fontawesome/__init__.py
fontawesome/generate.py
fontawesome/icons.py
fontawesome-5.10.1.post1.dist-info/METADATA
fontawesome-5.10.1.post1.dist-info/WHEEL
fontawesome-5.10.1.post1.dist-info/top_level.txt
fontawesome-5.10.1.post1.dist-info/RECORD
