Metadata-Version: 1.2
Name: fontawesome
Version: 5.10.1.post1
Summary: The Font Awesome icon set for python
Home-page: https://github.com/justbuchanan/fontawesome-python
Author: Justin Buchanan
Author-email: justbuchanan@gmail.com
Maintainer: Justin Buchanan
Maintainer-email: justbuchanan@gmail.com
License: Code: Apache License, Version 2.0, Icons: SIL OFL 1.1
Platform: UNKNOWN
Classifier: Environment :: Console
Classifier: Programming Language :: Python :: 2.7
Classifier: Programming Language :: Python :: 3
Classifier: Programming Language :: Python :: 3.4
